awslabs/__init__.py
awslabs/aws_appsync_mcp_server/__init__.py
awslabs/aws_appsync_mcp_server/decorators.py
awslabs/aws_appsync_mcp_server/helpers.py
awslabs/aws_appsync_mcp_server/server.py
awslabs/aws_appsync_mcp_server/validators.py
awslabs/aws_appsync_mcp_server/operations/__init__.py
awslabs/aws_appsync_mcp_server/operations/create_api.py
awslabs/aws_appsync_mcp_server/operations/create_api_cache.py
awslabs/aws_appsync_mcp_server/operations/create_api_key.py
awslabs/aws_appsync_mcp_server/operations/create_channel_namespace.py
awslabs/aws_appsync_mcp_server/operations/create_datasource.py
awslabs/aws_appsync_mcp_server/operations/create_domain_name.py
awslabs/aws_appsync_mcp_server/operations/create_function.py
awslabs/aws_appsync_mcp_server/operations/create_graphql_api.py
awslabs/aws_appsync_mcp_server/operations/create_resolver.py
awslabs/aws_appsync_mcp_server/operations/create_schema.py
awslabs/aws_appsync_mcp_server/tools/__init__.py
awslabs/aws_appsync_mcp_server/tools/create_api.py
awslabs/aws_appsync_mcp_server/tools/create_api_cache.py
awslabs/aws_appsync_mcp_server/tools/create_api_key.py
awslabs/aws_appsync_mcp_server/tools/create_channel_namespace.py
awslabs/aws_appsync_mcp_server/tools/create_datasource.py
awslabs/aws_appsync_mcp_server/tools/create_domain_name.py
awslabs/aws_appsync_mcp_server/tools/create_function.py
awslabs/aws_appsync_mcp_server/tools/create_graphql_api.py
awslabs/aws_appsync_mcp_server/tools/create_resolver.py
awslabs/aws_appsync_mcp_server/tools/create_schema.py
awslabs_aws_appsync_mcp_server-0.1.7.dist-info/METADATA
awslabs_aws_appsync_mcp_server-0.1.7.dist-info/WHEEL
awslabs_aws_appsync_mcp_server-0.1.7.dist-info/entry_points.txt
awslabs_aws_appsync_mcp_server-0.1.7.dist-info/licenses/LICENSE
awslabs_aws_appsync_mcp_server-0.1.7.dist-info/licenses/NOTICE
awslabs_aws_appsync_mcp_server-0.1.7.dist-info/RECORD
